MANIFEST.in
README.rst
pytest_oerp.py
setup.py
pytest_oerp.egg-info/PKG-INFO
pytest_oerp.egg-info/SOURCES.txt
pytest_oerp.egg-info/dependency_links.txt
pytest_oerp.egg-info/entry_points.txt
pytest_oerp.egg-info/requires.txt
pytest_oerp.egg-info/top_level.txt