Metadata-Version: 1.0
Name: pytest-oerp
Version: 0.2.0
Summary: pytest plugin to test OpenERP modules
Home-page: http://github.com/santagada/pytest-oerp/
Author: Leonardo Santagada
Author-email: santagada@gmail.com
License: Affero GPL 3
Platform: UNKNOWN
Classifier: Development Status :: 3 - Alpha
Classifier: Topic :: Software Development :: Testing
Classifier: License :: OSI Approved :: GNU Affero General Public License v3
Classifier: Intended Audience :: Developers
Classifier: Operating System :: OS Independent
